sensorcore/__init__.py
sensorcore/sensor/__init__.py
sensorcore/sensor/sensor.py
sensorcore/sensor/camera/__init__.py
sensorcore/sensor/camera/camera.py
sensorcore-0.0.1.dist-info/METADATA
sensorcore-0.0.1.dist-info/WHEEL
sensorcore-0.0.1.dist-info/top_level.txt
sensorcore-0.0.1.dist-info/RECORD
