Metadata-Version: 2.1
Name: sensorcore
Version: 0.0.1
Summary: A Python package for sensor calibration and validation
Author-email: Alix Leroy <alix.leroy@calibpro.com>
Project-URL: Homepage, https://calibpro.com
Classifier: Programming Language :: Python :: 3
Classifier: License :: OSI Approved :: MIT License
Classifier: Operating System :: OS Independent
Requires-Python: >=3.7
